tinkoff_acquiring_api/__init__.py
tinkoff_acquiring_api/api.py
tinkoff_acquiring_api/exceptions.py
tinkoff_acquiring_api-0.1.3.dist-info/LICENSE
tinkoff_acquiring_api-0.1.3.dist-info/METADATA
tinkoff_acquiring_api-0.1.3.dist-info/WHEEL
tinkoff_acquiring_api-0.1.3.dist-info/top_level.txt
tinkoff_acquiring_api-0.1.3.dist-info/RECORD
