Metadata-Version: 2.1
Name: tinkoff-acquiring-api
Version: 0.1.3
Summary: Tinkoff Acquiring API client for Python
Home-page: https://github.com/saliy/tinkoff-acquiring-api
Author: Artur Saliy
Author-email: artur.saliy@gmail.com
License: MIT
Project-URL: Documentation, https://github.com/saliy/tinkoff-acquiring-api
Project-URL: Bug Reports, https://github.com/saliy/tinkoff-acquiring-api/issues
Project-URL: Source Code, https://github.com/saliy/tinkoff-acquiring-api
Keywords: tinkoff,tinkoff api,tinkoff acquiring
Classifier: Development Status :: 1 - Planning
Classifier: Intended Audience :: Developers
Classifier: Topic :: Software Development :: Libraries
Classifier: Programming Language :: Python :: 3
Classifier: Programming Language :: Python :: 3.6
Classifier: Programming Language :: Python :: 3.7
Classifier: Programming Language :: Python :: 3.8
Classifier: Programming Language :: Python :: 3.9
Classifier: Programming Language :: Python :: 3 :: Only
Classifier: License :: OSI Approved :: MIT License
Classifier: Operating System :: OS Independent
Requires-Python: >=3.6
License-File: LICENSE
Requires-Dist: requests
Provides-Extra: dev
Requires-Dist: check-manifest ; extra == 'dev'
